{"board": [[[1, 1, 1, 1], [1, 0, 0, 1], [0, 0, 0, 1], [0, 0, 0, 1], [0, 0, 0, 1], [0, 0, 0, 1], [0, 0, 0, 1], [0, 0, 0, 1], [0, 0, 0, 1], [0, 0, 0, 1], [0, 1, 0, 1], [0, 0, 0, 1], [0, 0, 0, 1], [0, 0, 0, 1], [0, 0, 0, 1], [0, 0, 1, 1]], [[1, 0, 0, 1], [0, 0, 0, 0], [0, 0, 0, 0], [0, 0, 0, 0], [0, 0, 0, 0], [0, 0, 0, 0], [0, 0, 0, 0], [0, 0, 0, 0], [0, 0, 0, 0], [0, 0, 1, 0], [1, 1, 0, 1], [0, 0, 0, 0], [0, 0, 0, 0], [0, 0, 0, 0], [0, 0, 0, 0], [0, 0, 1, 0]], [[1, 0, 0, 0], [0, 1, 1, 0], [1, 0, 0, 0], [0, 0, 0, 0], [0, 1, 0, 0], [0, 0, 0, 0], [0, 0, 0, 0], [0, 0, 0, 0], [0, 0, 0, 0], [0, 0, 0, 0], [0, 0, 0, 1], [0, 0, 0, 0], [0, 0, 0, 0], [0, 0, 0, 0], [0, 0, 0, 0], [0, 0, 1, 0]], [[1, 0, 0, 0], [0, 0, 0, 1], [0, 1, 0, 0], [0, 0, 0, 0], [0, 0, 1, 1], [1, 0, 0, 0], [0, 0, 0, 0], [0, 0, 0, 0], [0, 0, 0, 0], [0, 0, 0, 0], [0, 0, 0, 0], [0, 0, 0, 0], [0, 0, 0, 0], [0, 1, 1, 0], [1, 0, 0, 0], [0, 0, 1, 0]], [[1, 0, 0, 0], [0, 0, 0, 0], [0, 0, 1, 1], [1, 0, 0, 0], [0, 0, 0, 0], [0, 0, 0, 0], [0, 0, 0, 0], [0, 0, 0, 0], [0, 0, 0, 0], [0, 0, 0, 0], [0, 0, 0, 0], [0, 0, 0, 0], [0, 0, 0, 0], [0, 0, 0, 1], [0, 0, 0, 0], [0, 0, 1, 0]], [[1, 0, 0, 0], [0, 1, 1, 0], [1, 0, 0, 0], [0, 0, 1, 0], [1, 1, 0, 0], [0, 0, 0, 0], [0, 0, 0, 0], [0, 0, 0, 0], [0, 0, 0, 0], [0, 0, 0, 0], [0, 1, 1, 0], [1, 0, 0, 0], [0, 1, 0, 0], [0, 0, 0, 0], [0, 1, 1, 0], [1, 0, 1, 0]], [[1, 0, 0, 0], [0, 1, 1, 1], [1, 0, 0, 0], [0, 0, 0, 0], [0, 1, 1, 1], [1, 0, 0, 0], [0, 0, 0, 0], [0, 1, 0, 0], [0, 1, 0, 0], [0, 0, 1, 0], [1, 1, 0, 1], [0, 1, 1, 0], [1, 0, 0, 1], [0, 0, 0, 0], [0, 0, 0, 1], [0, 0, 1, 0]], [[1, 1, 0, 0], [0, 0, 0, 1], [0, 0, 0, 0], [0, 0, 1, 0], [1, 1, 1, 1], [1, 1, 0, 0], [0, 0, 1, 0], [1, 1, 1, 1], [1, 1, 1, 1], [1, 0, 0, 0], [0, 0, 1, 1], [1, 0, 0, 1], [0, 0, 0, 0], [0, 0, 0, 0], [0, 0, 0, 0], [0, 0, 1, 0]], [[1, 0, 0, 1], [0, 0, 0, 0], [0, 1, 0, 0], [0, 0, 0, 0], [0, 0, 0, 1], [0, 0, 0, 1], [0, 0, 1, 0], [1, 1, 1, 1], [1, 1, 1, 1], [1, 0, 0, 0], [0, 0, 0, 0], [0, 0, 0, 0], [0, 0, 0, 0], [0, 0, 0, 0], [0, 0, 0, 0], [0, 0, 1, 0]], [[1, 0, 0, 0], [0, 0, 0, 0], [0, 0, 1, 1], [1, 0, 0, 0], [0, 0, 0, 0], [0, 0, 0, 0], [0, 1, 0, 0], [0, 0, 0, 1], [0, 0, 0, 1], [0, 0, 0, 0], [0, 0, 0, 0], [0, 0, 0, 0], [0, 0, 0, 0], [0, 0, 0, 0], [0, 0, 0, 0], [0, 0, 1, 0]], [[1, 0, 0, 0], [0, 0, 0, 0], [0, 0, 0, 0], [0, 0, 0, 0], [0, 0, 0, 0], [0, 0, 0, 0], [0, 0, 1, 1], [1, 0, 0, 0], [0, 0, 0, 0], [0, 0, 0, 0], [0, 0, 0, 0], [0, 0, 0, 0], [0, 0, 0, 0], [0, 0, 0, 0], [0, 0, 0, 0], [0, 0, 1, 0]], [[1, 0, 0, 0], [0, 0, 0, 0], [0, 0, 0, 0], [0, 0, 0, 0], [0, 0, 0, 0], [0, 0, 0, 0], [0, 0, 0, 0], [0, 0, 0, 0], [0, 0, 0, 0], [0, 0, 0, 0], [0, 0, 1, 0], [1, 1, 0, 0], [0, 0, 0, 0], [0, 0, 0, 0], [0, 0, 0, 0], [0, 0, 1, 0]], [[1, 0, 0, 0], [0, 0, 0, 0], [0, 0, 0, 0], [0, 0, 0, 0], [0, 0, 0, 0], [0, 0, 0, 0], [0, 0, 0, 0], [0, 0, 0, 0], [0, 0, 0, 0], [0, 0, 0, 0], [0, 0, 0, 0], [0, 0, 0, 1], [0, 0, 0, 0], [0, 0, 0, 0], [0, 0, 0, 0], [0, 0, 1, 0]], [[1, 0, 0, 0], [0, 0, 0, 0], [0, 1, 0, 0], [0, 0, 0, 0], [0, 0, 0, 0], [0, 0, 0, 0], [0, 0, 0, 0], [0, 0, 0, 0], [0, 0, 0, 0], [0, 0, 0, 0], [0, 1, 0, 0], [0, 0, 0, 0], [0, 0, 0, 0], [0, 0, 0, 0], [0, 0, 0, 0], [0, 1, 1, 0]], [[1, 0, 0, 0], [0, 0, 0, 0], [0, 0, 1, 1], [1, 1, 0, 0], [0, 0, 0, 0], [0, 0, 0, 0], [0, 0, 0, 0], [0, 0, 0, 0], [0, 0, 0, 0], [0, 0, 1, 0], [1, 1, 1, 1], [1, 0, 0, 0], [0, 0, 0, 0], [0, 0, 0, 0], [0, 0, 1, 0], [1, 1, 1, 1]], [[1, 1, 0, 0], [0, 1, 0, 0], [0, 1, 0, 0], [0, 1, 1, 1], [1, 1, 0, 0], [0, 1, 0, 0], [0, 1, 0, 0], [0, 1, 0, 0], [0, 1, 0, 0], [0, 1, 0, 0], [0, 1, 0, 1], [0, 1, 0, 0], [0, 1, 0, 0], [0, 1, 0, 0], [0, 1, 0, 0], [0, 1, 1, 1]]], "baseimg": "problems/117_base.png", "img": "problems/117.png", "goalpos": [1, 15], "robotpos": [[6, 8], [4, 8], [13, 14], [10, 0], [11, 2]], "mainrobot": 0, "answer": ["7", "0 5 6", "0 5 0", "0 15 0", "0 15 13", "1 15 4", "1 15 0", "0 15 1", ""]}