{"board": [[[1, 0, 0, 1], [0, 0, 0, 1], [0, 1, 1, 1], [1, 0, 0, 1], [0, 0, 0, 1], [0, 0, 0, 1], [0, 0, 1, 1], [1, 0, 0, 1], [0, 0, 0, 1], [0, 0, 0, 1], [0, 1, 0, 1], [0, 0, 0, 1], [0, 0, 0, 1], [0, 0, 0, 1], [0, 0, 0, 1], [0, 0, 1, 1]], [[1, 1, 0, 0], [0, 0, 0, 0], [0, 1, 1, 1], [1, 0, 0, 0], [0, 0, 0, 0], [0, 0, 0, 0], [0, 0, 1, 0], [1, 1, 0, 0], [0, 0, 0, 0], [0, 0, 0, 0], [0, 0, 1, 1], [1, 0, 0, 0], [0, 0, 0, 0], [0, 0, 0, 0], [0, 0, 0, 0], [0, 0, 1, 0]], [[1, 1, 0, 1], [0, 0, 0, 0], [0, 0, 0, 1], [0, 0, 0, 0], [0, 0, 0, 0], [0, 0, 0, 0], [0, 0, 0, 0], [0, 0, 0, 1], [0, 0, 0, 0], [0, 0, 0, 0], [0, 0, 0, 0], [0, 0, 0, 0], [0, 0, 0, 0], [0, 0, 0, 0], [0, 0, 0, 0], [0, 0, 1, 0]], [[1, 0, 0, 1], [0, 0, 0, 0], [0, 0, 0, 0], [0, 0, 0, 0], [0, 0, 0, 0], [0, 0, 0, 0], [0, 0, 0, 0], [0, 0, 0, 0], [0, 1, 0, 0], [0, 1, 1, 0], [1, 0, 0, 0], [0, 0, 0, 0], [0, 0, 0, 0], [0, 0, 0, 0], [0, 0, 0, 0], [0, 0, 1, 0]], [[1, 0, 0, 0], [0, 0, 0, 0], [0, 1, 0, 0], [0, 0, 0, 0], [0, 0, 0, 0], [0, 0, 0, 0], [0, 0, 0, 0], [0, 0, 1, 0], [1, 0, 0, 1], [0, 1, 0, 1], [0, 0, 0, 0], [0, 0, 0, 0], [0, 1, 1, 0], [1, 1, 0, 0], [0, 0, 0, 0], [0, 0, 1, 0]], [[1, 0, 0, 0], [0, 0, 1, 0], [1, 0, 0, 1], [0, 0, 0, 0], [0, 0, 0, 0], [0, 1, 0, 0], [0, 0, 0, 0], [0, 0, 0, 0], [0, 0, 1, 0], [1, 1, 0, 1], [0, 0, 0, 0], [0, 0, 0, 0], [0, 0, 0, 1], [0, 0, 1, 1], [1, 0, 0, 0], [0, 0, 1, 0]], [[1, 0, 0, 0], [0, 0, 0, 0], [0, 0, 0, 0], [0, 0, 0, 0], [0, 0, 1, 0], [1, 0, 0, 1], [0, 0, 0, 0], [0, 1, 0, 0], [0, 1, 0, 0], [0, 0, 1, 1], [1, 1, 0, 0], [0, 0, 0, 0], [0, 0, 0, 0], [0, 1, 0, 0], [0, 0, 0, 0], [0, 0, 1, 0]], [[1, 0, 0, 0], [0, 0, 0, 0], [0, 0, 0, 0], [0, 1, 1, 0], [1, 0, 0, 0], [0, 0, 0, 0], [0, 0, 1, 0], [1, 1, 1, 1], [1, 1, 1, 1], [1, 0, 1, 0], [1, 0, 0, 1], [0, 0, 0, 0], [0, 0, 1, 0], [1, 0, 0, 1], [0, 1, 0, 0], [0, 0, 1, 0]], [[1, 0, 0, 0], [0, 0, 0, 0], [0, 0, 0, 0], [0, 0, 0, 1], [0, 0, 0, 0], [0, 0, 0, 0], [0, 1, 1, 0], [1, 1, 1, 1], [1, 1, 1, 1], [1, 0, 0, 0], [0, 0, 0, 0], [0, 0, 0, 0], [0, 0, 0, 0], [0, 0, 1, 0], [1, 1, 0, 1], [0, 0, 1, 0]], [[1, 0, 0, 0], [0, 0, 0, 0], [0, 0, 0, 0], [0, 0, 0, 0], [0, 0, 0, 0], [0, 0, 1, 0], [1, 0, 0, 1], [0, 1, 0, 1], [0, 0, 0, 1], [0, 0, 0, 0], [0, 0, 0, 0], [0, 0, 0, 0], [0, 0, 0, 0], [0, 0, 0, 0], [0, 0, 1, 1], [1, 0, 1, 0]], [[1, 0, 0, 0], [0, 0, 0, 0], [0, 0, 0, 0], [0, 0, 0, 0], [0, 0, 0, 0], [0, 0, 0, 0], [0, 0, 0, 0], [0, 0, 1, 1], [1, 0, 1, 0], [1, 1, 0, 0], [0, 0, 0, 0], [0, 0, 0, 0], [0, 0, 0, 0], [0, 0, 0, 0], [0, 0, 0, 0], [0, 0, 1, 0]], [[1, 0, 0, 0], [0, 0, 0, 0], [0, 0, 0, 0], [0, 0, 0, 0], [0, 0, 0, 0], [0, 0, 0, 0], [0, 0, 0, 0], [0, 0, 0, 0], [0, 0, 0, 0], [0, 0, 0, 1], [0, 0, 0, 0], [0, 0, 0, 0], [0, 0, 0, 0], [0, 0, 1, 0], [1, 1, 0, 0], [0, 0, 1, 0]], [[1, 0, 0, 0], [0, 0, 0, 0], [0, 0, 0, 0], [0, 0, 0, 0], [0, 0, 0, 0], [0, 0, 0, 0], [0, 0, 0, 0], [0, 0, 0, 0], [0, 0, 0, 0], [0, 0, 0, 0], [0, 0, 0, 0], [0, 0, 0, 0], [0, 0, 0, 0], [0, 0, 0, 0], [0, 0, 0, 1], [0, 0, 1, 0]], [[1, 0, 0, 0], [0, 0, 0, 0], [0, 0, 0, 0], [0, 0, 0, 0], [0, 0, 0, 0], [0, 0, 0, 0], [0, 0, 0, 0], [0, 0, 0, 0], [0, 0, 0, 0], [0, 0, 0, 0], [0, 0, 0, 0], [0, 0, 0, 0], [0, 0, 0, 0], [0, 0, 0, 0], [0, 0, 0, 0], [0, 1, 1, 0]], [[1, 0, 0, 0], [0, 0, 0, 0], [0, 0, 0, 0], [0, 0, 0, 0], [0, 0, 0, 0], [0, 0, 0, 0], [0, 0, 0, 0], [0, 0, 0, 0], [0, 1, 0, 0], [0, 0, 0, 0], [0, 0, 0, 0], [0, 0, 0, 0], [0, 0, 0, 0], [0, 0, 0, 0], [0, 0, 0, 0], [0, 0, 1, 1]], [[1, 1, 0, 0], [0, 1, 0, 0], [0, 1, 0, 0], [0, 1, 0, 0], [0, 1, 0, 0], [0, 1, 0, 0], [0, 1, 0, 0], [0, 1, 0, 0], [0, 1, 1, 1], [1, 1, 0, 0], [0, 1, 0, 0], [0, 1, 0, 0], [0, 1, 0, 0], [0, 1, 0, 0], [0, 1, 0, 0], [0, 1, 1, 0]]], "baseimg": "problems/1522_base.png", "img": "problems/1522.png", "goalpos": [9, 1], "robotpos": [[14, 5], [1, 5], [13, 12], [11, 1], [0, 9]], "mainrobot": 0, "answer": ["9", "0 0 14", "1 6 1", "1 6 8", "1 0 8", "0 0 9", "0 5 9", "2 0 13", "2 0 9", "0 1 9", ""]}