{"board": [[[1, 0, 0, 1], [0, 0, 1, 1], [1, 0, 0, 1], [0, 0, 1, 1], [1, 0, 0, 1], [0, 0, 0, 1], [0, 1, 1, 1], [1, 0, 0, 1], [0, 0, 0, 1], [0, 0, 0, 1], [0, 0, 0, 1], [0, 0, 0, 1], [0, 0, 0, 1], [0, 0, 0, 1], [0, 0, 0, 1], [0, 0, 1, 1]], [[1, 0, 0, 0], [0, 0, 0, 0], [0, 0, 0, 0], [0, 0, 0, 0], [0, 0, 0, 0], [0, 0, 0, 0], [0, 0, 0, 1], [0, 0, 0, 0], [0, 1, 1, 0], [1, 0, 0, 0], [0, 0, 1, 0], [1, 1, 0, 0], [0, 0, 0, 0], [0, 0, 0, 0], [0, 0, 0, 0], [0, 1, 1, 0]], [[1, 1, 1, 0], [1, 1, 0, 0], [0, 0, 0, 0], [0, 0, 0, 0], [0, 0, 0, 0], [0, 0, 1, 0], [1, 1, 0, 0], [0, 0, 0, 0], [0, 0, 1, 1], [1, 1, 0, 0], [0, 0, 0, 0], [0, 0, 0, 1], [0, 0, 0, 0], [0, 0, 0, 0], [0, 0, 0, 0], [0, 0, 1, 1]], [[1, 1, 1, 1], [1, 0, 0, 1], [0, 0, 0, 0], [0, 0, 0, 0], [0, 0, 0, 0], [0, 0, 0, 0], [0, 0, 0, 1], [0, 0, 0, 0], [0, 0, 1, 0], [1, 0, 0, 1], [0, 0, 0, 0], [0, 0, 0, 0], [0, 0, 0, 0], [0, 0, 0, 0], [0, 0, 0, 0], [0, 0, 1, 0]], [[1, 0, 0, 1], [0, 0, 0, 0], [0, 0, 0, 0], [0, 0, 0, 0], [0, 0, 0, 0], [0, 0, 0, 0], [0, 1, 0, 0], [0, 1, 0, 0], [0, 0, 0, 0], [0, 0, 0, 0], [0, 0, 0, 0], [0, 0, 0, 0], [0, 0, 0, 0], [0, 0, 1, 0], [1, 1, 0, 0], [0, 0, 1, 0]], [[1, 0, 0, 0], [0, 0, 0, 0], [0, 0, 0, 0], [0, 0, 0, 0], [0, 1, 0, 0], [0, 0, 1, 0], [1, 0, 0, 1], [0, 0, 1, 1], [1, 0, 0, 0], [0, 0, 0, 0], [0, 0, 0, 0], [0, 0, 0, 0], [0, 0, 0, 0], [0, 0, 0, 0], [0, 0, 0, 1], [0, 0, 1, 0]], [[1, 1, 0, 0], [0, 0, 0, 0], [0, 0, 0, 0], [0, 0, 1, 0], [1, 0, 0, 1], [0, 0, 0, 0], [0, 0, 0, 0], [0, 1, 0, 0], [0, 1, 1, 0], [1, 1, 0, 0], [0, 0, 0, 0], [0, 0, 0, 0], [0, 0, 0, 0], [0, 0, 0, 0], [0, 0, 0, 0], [0, 0, 1, 0]], [[1, 0, 0, 1], [0, 0, 0, 0], [0, 0, 0, 0], [0, 0, 0, 0], [0, 0, 0, 0], [0, 0, 0, 0], [0, 0, 1, 0], [1, 1, 1, 1], [1, 1, 1, 1], [1, 0, 0, 1], [0, 0, 0, 0], [0, 0, 0, 0], [0, 1, 1, 0], [1, 0, 0, 0], [0, 0, 0, 0], [0, 0, 1, 0]], [[1, 0, 0, 0], [0, 0, 0, 0], [0, 0, 0, 0], [0, 0, 0, 0], [0, 0, 0, 0], [0, 0, 0, 0], [0, 0, 1, 0], [1, 1, 1, 1], [1, 1, 1, 1], [1, 0, 1, 0], [1, 1, 0, 0], [0, 0, 0, 0], [0, 0, 0, 1], [0, 0, 0, 0], [0, 0, 0, 0], [0, 0, 1, 0]], [[1, 0, 0, 0], [0, 0, 0, 0], [0, 0, 0, 0], [0, 0, 0, 0], [0, 0, 0, 0], [0, 0, 1, 0], [1, 1, 0, 0], [0, 0, 0, 1], [0, 0, 0, 1], [0, 0, 0, 0], [0, 0, 0, 1], [0, 0, 0, 0], [0, 0, 0, 0], [0, 0, 0, 0], [0, 0, 0, 0], [0, 0, 1, 0]], [[1, 0, 0, 0], [0, 0, 0, 0], [0, 0, 0, 0], [0, 0, 0, 0], [0, 0, 0, 0], [0, 0, 0, 0], [0, 0, 0, 1], [0, 0, 0, 0], [0, 0, 0, 0], [0, 0, 0, 0], [0, 1, 1, 0], [1, 0, 0, 0], [0, 0, 0, 0], [0, 0, 0, 0], [0, 0, 0, 0], [0, 0, 1, 0]], [[1, 0, 0, 0], [0, 0, 0, 0], [0, 0, 0, 0], [0, 0, 0, 0], [0, 0, 0, 0], [0, 0, 0, 0], [0, 0, 0, 0], [0, 0, 0, 0], [0, 0, 0, 0], [0, 0, 0, 0], [0, 1, 0, 1], [0, 0, 0, 0], [0, 0, 0, 0], [0, 0, 0, 0], [0, 0, 0, 0], [0, 0, 1, 0]], [[1, 0, 0, 0], [0, 0, 0, 0], [0, 0, 0, 0], [0, 1, 1, 0], [1, 1, 0, 0], [0, 0, 0, 0], [0, 0, 0, 0], [0, 0, 0, 0], [0, 0, 0, 0], [0, 0, 0, 0], [0, 0, 1, 1], [1, 0, 0, 0], [0, 0, 0, 0], [0, 0, 0, 0], [0, 0, 1, 0], [1, 1, 1, 0]], [[1, 0, 0, 0], [0, 0, 0, 0], [0, 0, 0, 0], [0, 0, 1, 1], [1, 0, 0, 1], [0, 1, 0, 0], [0, 0, 0, 0], [0, 0, 0, 0], [0, 0, 0, 0], [0, 0, 0, 0], [0, 0, 1, 0], [1, 1, 0, 0], [0, 0, 0, 0], [0, 0, 0, 0], [0, 0, 0, 0], [0, 0, 1, 1]], [[1, 0, 0, 0], [0, 0, 0, 0], [0, 0, 0, 0], [0, 0, 0, 0], [0, 0, 1, 0], [1, 0, 0, 1], [0, 0, 0, 0], [0, 0, 0, 0], [0, 0, 0, 0], [0, 0, 0, 0], [0, 0, 1, 0], [1, 1, 0, 1], [0, 0, 0, 0], [0, 0, 0, 0], [0, 0, 0, 0], [0, 0, 1, 0]], [[1, 1, 0, 0], [0, 1, 1, 0], [1, 1, 0, 0], [0, 1, 0, 0], [0, 1, 0, 0], [0, 1, 0, 0], [0, 1, 0, 0], [0, 1, 1, 0], [1, 1, 0, 0], [0, 1, 0, 0], [0, 1, 0, 0], [0, 1, 0, 1], [0, 1, 0, 0], [0, 1, 0, 0], [0, 1, 0, 0], [0, 1, 1, 0]]], "baseimg": "problems/2001_base.png", "img": "problems/2001.png", "goalpos": [2, 8], "robotpos": [[4, 5], [11, 4], [8, 15], [11, 2], [0, 15]], "mainrobot": 4, "answer": ["6", "4 7 0", "4 7 4", "4 6 4", "4 6 3", "4 8 3", "4 8 2", ""]}