{"board": [[[1, 0, 1, 1], [1, 0, 0, 1], [0, 0, 1, 1], [1, 1, 1, 1], [1, 1, 0, 1], [0, 0, 0, 1], [0, 0, 0, 1], [0, 0, 0, 1], [0, 0, 0, 1], [0, 0, 0, 1], [0, 0, 0, 1], [0, 0, 0, 1], [0, 1, 0, 1], [0, 0, 0, 1], [0, 0, 1, 1], [1, 0, 1, 1]], [[1, 0, 0, 0], [0, 0, 0, 0], [0, 0, 0, 0], [0, 0, 1, 1], [1, 0, 1, 1], [1, 1, 0, 0], [0, 0, 0, 0], [0, 0, 0, 0], [0, 0, 0, 0], [0, 0, 1, 0], [1, 1, 0, 0], [0, 0, 1, 0], [1, 0, 0, 1], [0, 0, 0, 0], [0, 0, 0, 0], [0, 0, 1, 0]], [[1, 1, 1, 0], [1, 0, 0, 0], [0, 0, 0, 0], [0, 0, 0, 0], [0, 1, 0, 0], [0, 0, 0, 1], [0, 0, 0, 0], [0, 0, 0, 0], [0, 0, 0, 0], [0, 0, 0, 0], [0, 0, 0, 1], [0, 0, 0, 0], [0, 0, 0, 0], [0, 0, 0, 0], [0, 0, 0, 0], [0, 0, 1, 0]], [[1, 0, 0, 1], [0, 0, 0, 0], [0, 0, 0, 0], [0, 0, 1, 0], [1, 1, 1, 1], [1, 0, 0, 0], [0, 0, 0, 0], [0, 0, 0, 0], [0, 0, 0, 0], [0, 0, 0, 0], [0, 0, 0, 0], [0, 0, 0, 0], [0, 0, 0, 0], [0, 0, 0, 0], [0, 0, 0, 0], [0, 1, 1, 0]], [[1, 0, 0, 0], [0, 0, 0, 0], [0, 0, 0, 0], [0, 0, 0, 0], [0, 1, 0, 1], [0, 0, 0, 0], [0, 0, 0, 0], [0, 0, 0, 0], [0, 0, 0, 0], [0, 1, 0, 0], [0, 0, 0, 0], [0, 0, 0, 0], [0, 0, 0, 0], [0, 0, 0, 0], [0, 1, 0, 0], [0, 0, 1, 1]], [[1, 0, 0, 0], [0, 0, 0, 0], [0, 0, 0, 0], [0, 0, 1, 0], [1, 0, 0, 1], [0, 0, 0, 0], [0, 0, 0, 0], [0, 0, 0, 0], [0, 0, 0, 0], [0, 0, 1, 1], [1, 0, 0, 0], [0, 0, 0, 0], [0, 1, 0, 0], [0, 0, 0, 0], [0, 0, 1, 1], [1, 0, 1, 0]], [[1, 0, 0, 0], [0, 0, 1, 0], [1, 1, 0, 0], [0, 0, 0, 0], [0, 0, 0, 0], [0, 0, 0, 0], [0, 0, 0, 0], [0, 1, 1, 0], [1, 1, 0, 0], [0, 0, 1, 0], [1, 1, 0, 0], [0, 0, 1, 0], [1, 0, 0, 1], [0, 0, 0, 0], [0, 0, 0, 0], [0, 0, 1, 0]], [[1, 0, 0, 0], [0, 0, 0, 0], [0, 0, 0, 1], [0, 0, 0, 0], [0, 0, 0, 0], [0, 0, 0, 0], [0, 0, 1, 0], [1, 1, 1, 1], [1, 1, 1, 1], [1, 0, 0, 0], [0, 0, 0, 1], [0, 0, 0, 0], [0, 0, 0, 0], [0, 0, 0, 0], [0, 0, 0, 0], [0, 0, 1, 0]], [[1, 0, 0, 0], [0, 0, 0, 0], [0, 0, 0, 0], [0, 0, 0, 0], [0, 0, 0, 0], [0, 1, 1, 0], [1, 1, 1, 0], [1, 1, 1, 1], [1, 1, 1, 1], [1, 1, 0, 0], [0, 0, 0, 0], [0, 0, 0, 0], [0, 0, 0, 0], [0, 0, 0, 0], [0, 0, 0, 0], [0, 0, 1, 0]], [[1, 0, 0, 0], [0, 0, 0, 0], [0, 0, 0, 0], [0, 0, 0, 0], [0, 0, 0, 0], [0, 0, 0, 1], [0, 0, 1, 1], [1, 0, 0, 1], [0, 0, 0, 1], [0, 0, 0, 1], [0, 0, 0, 0], [0, 1, 0, 0], [0, 0, 0, 0], [0, 0, 0, 0], [0, 0, 0, 0], [0, 0, 1, 0]], [[1, 0, 0, 0], [0, 0, 0, 0], [0, 0, 0, 0], [0, 0, 0, 0], [0, 0, 0, 0], [0, 0, 0, 0], [0, 0, 0, 0], [0, 0, 0, 0], [0, 0, 0, 0], [0, 0, 0, 0], [0, 0, 1, 0], [1, 0, 0, 1], [0, 0, 0, 0], [0, 0, 0, 0], [0, 0, 0, 0], [0, 0, 1, 0]], [[1, 0, 0, 0], [0, 0, 0, 0], [0, 0, 0, 0], [0, 0, 0, 0], [0, 0, 0, 0], [0, 0, 0, 0], [0, 0, 1, 0], [1, 1, 0, 0], [0, 0, 0, 0], [0, 0, 0, 0], [0, 0, 0, 0], [0, 0, 0, 0], [0, 1, 0, 0], [0, 0, 0, 0], [0, 0, 0, 0], [0, 0, 1, 0]], [[1, 0, 0, 0], [0, 0, 0, 0], [0, 0, 0, 0], [0, 0, 0, 0], [0, 1, 1, 0], [1, 0, 0, 0], [0, 0, 0, 0], [0, 0, 0, 1], [0, 1, 0, 0], [0, 0, 0, 0], [0, 0, 0, 0], [0, 0, 1, 0], [1, 1, 0, 1], [0, 1, 0, 0], [0, 0, 0, 0], [0, 0, 1, 0]], [[1, 0, 0, 0], [0, 0, 0, 0], [0, 0, 0, 0], [0, 0, 0, 0], [0, 0, 0, 1], [0, 0, 0, 0], [0, 0, 0, 0], [0, 0, 1, 0], [1, 0, 0, 1], [0, 0, 0, 0], [0, 0, 0, 0], [0, 0, 1, 0], [1, 0, 1, 1], [1, 0, 0, 1], [0, 0, 0, 0], [0, 0, 1, 0]], [[1, 0, 0, 0], [0, 0, 0, 0], [0, 0, 0, 0], [0, 0, 0, 0], [0, 0, 0, 0], [0, 0, 0, 0], [0, 0, 0, 0], [0, 0, 0, 0], [0, 0, 0, 0], [0, 0, 0, 0], [0, 0, 0, 0], [0, 0, 0, 0], [0, 0, 0, 0], [0, 0, 0, 0], [0, 0, 0, 0], [0, 0, 1, 0]], [[1, 1, 0, 0], [0, 1, 0, 0], [0, 1, 0, 0], [0, 1, 0, 0], [0, 1, 0, 0], [0, 1, 0, 0], [0, 1, 0, 0], [0, 1, 0, 0], [0, 1, 0, 0], [0, 1, 0, 0], [0, 1, 0, 0], [0, 1, 0, 0], [0, 1, 0, 0], [0, 1, 0, 0], [0, 1, 0, 0], [0, 1, 1, 0]]], "img": "problems/9.png", "goalpos": [6, 6], "robotpos": [[11, 15], [5, 11], [12, 1], [12, 4], [15, 12]], "mainrobot": 0, "answer": ["11", "0 15 15", "2 1 15", "4 2 15", "4 2 7", "0 2 15", "4 0 7", "0 2 7", "0 6 7", "0 6 0", "4 6 7", "0 6 6", ""]}